[
  {
    "full_name": "monproweb/mon-pro-web",
    "stargazers_count": 1,
    "open_issues_count": 0,
    "forks_count": 0
  },
  {
    "full_name": "monproweb/mon-pro-web",
    "stargazers_count": 1,
    "open_issues_count": 0,
    "forks_count": 0
  },
  {
    "full_name": "FormidableLabs/react-animations",
    "stargazers_count": 2958,
    "open_issues_count": 12,
    "forks_count": 162
  },
  {
    "full_name": "facebookexperimental/Recoil",
    "stargazers_count": 14815,
    "open_issues_count": 173,
    "forks_count": 729
  },
  {
    "full_name": "facebookexperimental/Recoil",
    "stargazers_count": 14815,
    "open_issues_count": 173,
    "forks_count": 729
  },
  {
    "full_name": "facebookexperimental/Recoil",
    "stargazers_count": 14815,
    "open_issues_count": 173,
    "forks_count": 729
  },
  {
    "full_name": "remirror/remirror",
    "stargazers_count": 1370,
    "open_issues_count": 91,
    "forks_count": 126
  }
]