[
  {
    "full_name": "graphql-go/relay",
    "stargazers_count": 393,
    "open_issues_count": 12,
    "forks_count": 61
  },
  {
    "full_name": "GoogleCloudPlatform/click-to-deploy",
    "stargazers_count": 614,
    "open_issues_count": 92,
    "forks_count": 368
  },
  {
    "full_name": "benawad/node-graphql-benchmarks",
    "stargazers_count": 510,
    "open_issues_count": 7,
    "forks_count": 76
  },
  {
    "full_name": "jkettmann/graphql-passport",
    "stargazers_count": 139,
    "open_issues_count": 9,
    "forks_count": 17
  },
  {
    "full_name": "Gherciu/react-p5",
    "stargazers_count": 442,
    "open_issues_count": 7,
    "forks_count": 44
  },
  {
    "full_name": "stream-labs/streamlabs-obs",
    "stargazers_count": 3760,
    "open_issues_count": 25,
    "forks_count": 610
  },
  {
    "full_name": "matteobruni/tsparticles",
    "stargazers_count": 3455,
    "open_issues_count": 26,
    "forks_count": 408
  },
  {
    "full_name": "adobe/react-spectrum",
    "stargazers_count": 6715,
    "open_issues_count": 385,
    "forks_count": 524
  },
  {
    "full_name": "GoogleCloudPlatform/community",
    "stargazers_count": 1670,
    "open_issues_count": 56,
    "forks_count": 1589
  },
  {
    "full_name": "ChainSafe/lodestar",
    "stargazers_count": 656,
    "open_issues_count": 240,
    "forks_count": 128
  },
  {
    "full_name": "NethermindEth/nethermind",
    "stargazers_count": 600,
    "open_issues_count": 228,
    "forks_count": 186
  },
  {
    "full_name": "prysmaticlabs/prysm",
    "stargazers_count": 2556,
    "open_issues_count": 212,
    "forks_count": 616
  },
  {
    "full_name": "ConsenSys/teku",
    "stargazers_count": 401,
    "open_issues_count": 110,
    "forks_count": 167
  },
  {
    "full_name": "sigp/lighthouse",
    "stargazers_count": 1727,
    "open_issues_count": 192,
    "forks_count": 371
  },
  {
    "full_name": "status-im/nimbus-eth2",
    "stargazers_count": 296,
    "open_issues_count": 173,
    "forks_count": 100
  },
  {
    "full_name": "gyf304/ethminer-m1",
    "stargazers_count": 427,
    "open_issues_count": 1,
    "forks_count": 100
  },
  {
    "full_name": "OpenKudos/python_client",
    "stargazers_count": 9,
    "open_issues_count": 2,
    "forks_count": 6
  },
  {
    "full_name": "OpenKudos/OpenKudos",
    "stargazers_count": 17,
    "open_issues_count": 8,
    "forks_count": 8
  },
  {
    "full_name": "gitcoinco/kudosbadges",
    "stargazers_count": 82,
    "open_issues_count": 239,
    "forks_count": 114
  },
  {
    "full_name": "codesponsor/codesponsor",
    "stargazers_count": 12,
    "open_issues_count": 41,
    "forks_count": 6
  },
  {
    "full_name": "gitcoinco/community",
    "stargazers_count": 25,
    "open_issues_count": 2,
    "forks_count": 17
  },
  {
    "full_name": "gitcoinco/skunkworks",
    "stargazers_count": 58,
    "open_issues_count": 216,
    "forks_count": 33
  },
  {
    "full_name": "gitcoinco/ios",
    "stargazers_count": 22,
    "open_issues_count": 14,
    "forks_count": 10
  },
  {
    "full_name": "gitcoinco/browser-extension",
    "stargazers_count": 47,
    "open_issues_count": 51,
    "forks_count": 29
  },
  {
    "full_name": "gitcoinco/GIPs",
    "stargazers_count": 12,
    "open_issues_count": 9,
    "forks_count": 8
  },
  {
    "full_name": "ccxt/ccxt",
    "stargazers_count": 24949,
    "open_issues_count": 794,
    "forks_count": 6107
  },
  {
    "full_name": "cloudflare/workers-rs",
    "stargazers_count": 1026,
    "open_issues_count": 34,
    "forks_count": 74
  },
  {
    "full_name": "cloudflare/worker-examples",
    "stargazers_count": 701,
    "open_issues_count": 30,
    "forks_count": 157
  },
  {
    "full_name": "cloudflare/cloudflared",
    "stargazers_count": 3126,
    "open_issues_count": 186,
    "forks_count": 358
  },
  {
    "full_name": "cloudflare/wrangler",
    "stargazers_count": 3044,
    "open_issues_count": 66,
    "forks_count": 371
  }
]